<?xml version="1.0" encoding="UTF-8"?>
<!--
The contents of this file are subject to the terms of the Common Development
and Distribution License (the License). You may not use this file except in
compliance with the License.

You can obtain a copy of the License at http://www.netbeans.org/cddl.html
or http://www.netbeans.org/cddl.txt.

When distributing Covered Code, include this CDDL Header Notice in each file
and include the License file at http://www.netbeans.org/cddl.txt.
If applicable, add the following below the CDDL Header, with the fields
enclosed by brackets [] replaced by your own identifying information:
"Portions Copyrighted [year] [name of copyright owner]"

The Original Software is NetBeans. The Initial Developer of the Original
Software is Sun Microsystems, Inc. Portions Copyright 1997-2006 Sun
Microsystems, Inc. All Rights Reserved.
-->
<!DOCTYPE apichanges PUBLIC "-//NetBeans//DTD API changes list 1.0//EN" "../../nbbuild/javadoctools/apichanges.dtd">
<apichanges>
    <apidefs>
        <apidef name="masterfs">MasterFileSystem API</apidef>
    </apidefs>
    <changes>
        <change id="added-support-for-local-history">
            <api name="masterfs"/>
            <summary><code>ProvidedExtensions.beforeChange</code> was added.</summary>
            <version major="1" minor="10"/>
            <date day="12" month="2" year="2007"/>
            <author login="rmatous"/>
            <compatibility addition="yes" binary="compatible" source="compatible" semantic="compatible" deprecation="no" deletion="no" modification="no"/>
            <description>
                <p>
                    <code>ProvidedExtensions.beforeChange</code>which is called by 
                    <code>MasterFileSystem</code> when <code>FileObject</code>
                    is going to be modified by asking for <code>OutputStream</code>.
                </p>                
            </description>
            <class package="org.netbeans.modules.masterfs.providers" name="ProvidedExtensions"/>
            <issue number="92676"/>
        </change>                        
        <change id="added-support-for-subversion-delete">
            <api name="masterfs"/>
            <summary><code>ProvidedExtensions.getDeleteHandler</code> was added.</summary>
            <version major="1" minor="9"/>
            <date day="8" month="8" year="2006"/>
            <author login="rmatous"/>
            <compatibility addition="yes" binary="compatible" source="compatible" semantic="compatible" deprecation="no" deletion="no" modification="no"/>
            <description>
                <p>
                    <code>ProvidedExtensions.getDeleteHandler</code> was added, which
                    is the way how to impose handlers for 
                    deleting into mastersfs implementation 
                    which was required by module org.netbeans.modules.subversion.
                </p>
            </description>
            <class package="org.netbeans.modules.masterfs.providers" name="ProvidedExtensions"/>
            <issue number="81510"/>
        </change>                
        <change id="added-support-for-subversion">
            <api name="masterfs"/>
            <summary><code>ProvidedExtensions</code> was added.</summary>
            <version major="1" minor="9"/>
            <date day="24" month="4" year="2006"/>
            <author login="rmatous"/>
            <compatibility addition="yes" binary="compatible" source="compatible" semantic="compatible" deprecation="no" deletion="no" modification="no"/>
            <description>
                <p>
                    <code>ProvidedExtensions</code> was added.
                    Registering subclass of <code>ProvidedExtensions</code> 
                    as a substitution of <code>InterceptionListener</code> is the way 
                    how to impose handlers for renaming and moving into mastersfs implementation 
                    which was required by module org.netbeans.modules.subversion.
                </p>
            </description>
            <class package="org.netbeans.modules.masterfs.providers" name="ProvidedExtensions"/>
            <issue number="73042"/>
        </change>
    </changes>
    <htmlcontents>
        <head>
        <title>Change History for the MasterFileSystem API</title>
        <link rel="stylesheet" href="prose.css" type="text/css"/>
        </head>
        <body>
            <p class="overviewlink">
                <a href="overview-summary.html">Overview</a>
            </p>
            <h1>Introduction</h1>

            <p>This document lists changes made to the <a href="@TOP@">MasterFileSystem API</a>.</p>
            <!-- The actual lists of changes, as summaries and details: -->

            <hr/><standard-changelists module-code-name="org.netbeans.modules.masterfs"/>

            <hr/><p>@FOOTER@</p>

        </body>
    </htmlcontents>
</apichanges>
