<?xml version="1.0" encoding="UTF-8"?>
<!--
DO NOT ALTER OR REMOVE COPYRIGHT NOTICES OR THIS HEADER.

Copyright 1997-2010 Oracle and/or its affiliates. All rights reserved.

Oracle and Java are registered trademarks of Oracle and/or its affiliates.
Other names may be trademarks of their respective owners.


The contents of this file are subject to the terms of either the GNU
General Public License Version 2 only ("GPL") or the Common
Development and Distribution License("CDDL") (collectively, the
"License"). You may not use this file except in compliance with the
License. You can obtain a copy of the License at
http://www.netbeans.org/cddl-gplv2.html
or nbbuild/licenses/CDDL-GPL-2-CP. See the License for the
specific language governing permissions and limitations under the
License.  When distributing the software, include this License Header
Notice in each file and include the License file at
nbbuild/licenses/CDDL-GPL-2-CP.  Oracle designates this
particular file as subject to the "Classpath" exception as provided
by Oracle in the GPL Version 2 section of the License file that
accompanied this code. If applicable, add the following below the
License Header, with the fields enclosed by brackets [] replaced by
your own identifying information:
"Portions Copyrighted [year] [name of copyright owner]"

Contributor(s):

The Original Software is NetBeans. The Initial Developer of the Original
Software is Sun Microsystems, Inc. Portions Copyright 2001-2006 Sun
Microsystems, Inc. All Rights Reserved.

If you wish your version of this file to be governed by only the CDDL
or only the GPL Version 2, indicate your decision by adding
"[Contributor] elects to include this software in this distribution
under the [CDDL or GPL Version 2] license." If you do not indicate a
single choice of license, a recipient has the option to distribute
your version of this file under either the CDDL, the GPL Version 2 or
to extend the choice of license to its licensees as provided above.
However, if you add GPL Version 2 code and therefore, elected the GPL
Version 2 license, then the option applies only if the new code is
made subject to such option by the copyright holder.
-->

<toolchaindefinition xmlns="http://www.netbeans.org/ns/cnd-toolchain-definition/1">
    <cpp>
        <compiler name="CC"/>
        <version flags="-V" fingerprint_flags="-Wd,-xide" fingerprint_pattern="#\s*__tool_build_number\s*(\w*)"/>
        <system_include_paths parser="Fingerprint"/>
        <important_flags flags="-O(\W|$|-])|-O0|-O1|-O2|-O3|-O4|-O5|-compat=.*|-fast|-fopenmp|-m64|-mt(\W|$|-])|-mt=.*|-native|-std=.*|-xO1|-xO2|-xO3|-xO4|-xO5|-xautopar|-xchar=.*|-xmaxopt=.*|-xopenmp(\W|$|-])|-xopenmp=.*"/>
        <system_macros parser="Fingerprint">
            <macro hide="true" stringvalue="__LINE__"/>
            <macro hide="true" stringvalue="__FILE__"/>
            <macro hide="true" stringvalue="__DATE__"/>
            <macro hide="true" stringvalue="__TIME__"/>
            
            <macro stringvalue="__NOVECTORSIZE__" flags="-O" hide="true"/>

            <macro stringvalue="__NOVECTORSIZE__" flags="-O0" hide="true"/>

            <macro stringvalue="__NOVECTORSIZE__" flags="-O1" hide="true"/>

            <macro stringvalue="__NOVECTORSIZE__" flags="-O2" hide="true"/>

            <macro stringvalue="__NOVECTORSIZE__" flags="-O3" hide="true"/>

            <macro stringvalue="__NOVECTORSIZE__" flags="-O4" hide="true"/>

            <macro stringvalue="__NOVECTORSIZE__" flags="-O5" hide="true"/>

            <macro stringvalue="__builtin_expect(e,x)=e" flags="-compat=g"/>
            <macro stringvalue="__SIZE_TYPE__=unsigned int" flags="-compat=g"/>
            <macro stringvalue="__PTRDIFF_TYPE__=int" flags="-compat=g"/>
            <macro stringvalue="__WCHAR_TYPE__=long" flags="-compat=g"/>
            <macro stringvalue="__gnuc_va_list=va_list" flags="-compat=g"/>
            <macro stringvalue="_GNU_SOURCE=1" flags="-compat=g"/>
            <macro stringvalue="__extension__" flags="-compat=g"/>
            <macro stringvalue="__restrict__" flags="-compat=g"/>
            <macro stringvalue="__restrict" flags="-compat=g"/>
            <macro stringvalue="__null=0" flags="-compat=g"/>
            <macro stringvalue="__SUNPRO_CC_COMPAT='G'" flags="-compat=g"/>
            <macro stringvalue="__cplusplus=1" flags="-compat=g"/>
            <macro stringvalue="__NOVECTORSIZE__" flags="-compat=g" hide="true"/>
            <macro stringvalue="_LARGEFILE64_SOURCE" flags="-compat=g" hide="true"/>
            <macro stringvalue="__builtin_huge_val" flags="-compat=g" hide="true"/>
            <macro stringvalue="__builtin_huge_valf" flags="-compat=g" hide="true"/>
            <macro stringvalue="__builtin_huge_vall" flags="-compat=g" hide="true"/>
            <macro stringvalue="__builtin_nan" flags="-compat=g" hide="true"/>
            <macro stringvalue="__builtin_fpclassify" flags="-compat=g" hide="true"/>

            <macro stringvalue="__NOVECTORSIZE__" flags="-fast" hide="true"/>

            <macro stringvalue="_REENTRANT=1" flags="-fopenmp"/>
            <macro stringvalue="_OPENMP=201307L" flags="-fopenmp"/>
            <macro stringvalue="__NOVECTORSIZE__" flags="-fopenmp" hide="true"/>

            <macro stringvalue="__x86_64=1" flags="-m64"/>
            <macro stringvalue="__x86_64__=1" flags="-m64"/>
            <macro stringvalue="__amd64=1" flags="-m64"/>
            <macro stringvalue="__amd64__=1" flags="-m64"/>
            <macro stringvalue="_LP64=1" flags="-m64"/>
            <macro stringvalue="__LP64__=1" flags="-m64"/>
            <macro stringvalue="__BUILTIN_VA_STRUCT=1" flags="-m64"/>
            <macro stringvalue="__i386" flags="-m64" hide="true"/>
            <macro stringvalue="__BUILTIN_VA_ARG_INCR" flags="-m64" hide="true"/>
            <macro stringvalue="i386" flags="-m64" hide="true"/>

            <macro stringvalue="_REENTRANT=1" flags="-mt"/>

            <macro stringvalue="_REENTRANT=1" flags="-mt=yes"/>

            <macro stringvalue="__NOVECTORSIZE__" flags="-native" hide="true"/>

            <macro stringvalue="__builtin_expect(e,x)=e" flags="-std=c++03"/>
            <macro stringvalue="__SIZE_TYPE__=unsigned int" flags="-std=c++03"/>
            <macro stringvalue="__PTRDIFF_TYPE__=int" flags="-std=c++03"/>
            <macro stringvalue="__WCHAR_TYPE__=long" flags="-std=c++03"/>
            <macro stringvalue="__gnuc_va_list=va_list" flags="-std=c++03"/>
            <macro stringvalue="_GNU_SOURCE=1" flags="-std=c++03"/>
            <macro stringvalue="__extension__" flags="-std=c++03"/>
            <macro stringvalue="__restrict__" flags="-std=c++03"/>
            <macro stringvalue="__restrict" flags="-std=c++03"/>
            <macro stringvalue="__null=0" flags="-std=c++03"/>
            <macro stringvalue="__SUNPRO_CC_COMPAT='G'" flags="-std=c++03"/>
            <macro stringvalue="__cplusplus=1" flags="-std=c++03"/>
            <macro stringvalue="__NOVECTORSIZE__" flags="-std=c++03" hide="true"/>
            <macro stringvalue="_LARGEFILE64_SOURCE" flags="-std=c++03" hide="true"/>
            <macro stringvalue="__builtin_huge_val" flags="-std=c++03" hide="true"/>
            <macro stringvalue="__builtin_huge_valf" flags="-std=c++03" hide="true"/>
            <macro stringvalue="__builtin_huge_vall" flags="-std=c++03" hide="true"/>
            <macro stringvalue="__builtin_nan" flags="-std=c++03" hide="true"/>
            <macro stringvalue="__builtin_fpclassify" flags="-std=c++03" hide="true"/>

            <macro stringvalue="__builtin_expect(e,x)=e" flags="-std=c++0x"/>
            <macro stringvalue="__decltype=decltype" flags="-std=c++0x"/>
            <macro stringvalue="__SIZE_TYPE__=unsigned int" flags="-std=c++0x"/>
            <macro stringvalue="__PTRDIFF_TYPE__=int" flags="-std=c++0x"/>
            <macro stringvalue="__WCHAR_TYPE__=long" flags="-std=c++0x"/>
            <macro stringvalue="__gnuc_va_list=va_list" flags="-std=c++0x"/>
            <macro stringvalue="_GNU_SOURCE=1" flags="-std=c++0x"/>
            <macro stringvalue="__extension__" flags="-std=c++0x"/>
            <macro stringvalue="__restrict__" flags="-std=c++0x"/>
            <macro stringvalue="__restrict" flags="-std=c++0x"/>
            <macro stringvalue="__null=0" flags="-std=c++0x"/>
            <macro stringvalue="__GXX_EXPERIMENTAL_CXX0X__=1" flags="-std=c++0x"/>
            <macro stringvalue="__SUNPRO_CC_COMPAT='G'" flags="-std=c++0x"/>
            <macro stringvalue="__cplusplus=201103L" flags="-std=c++0x"/>
            <macro stringvalue="__NOVECTORSIZE__" flags="-std=c++0x" hide="true"/>
            <macro stringvalue="_LARGEFILE64_SOURCE" flags="-std=c++0x" hide="true"/>
            <macro stringvalue="__builtin_huge_val" flags="-std=c++0x" hide="true"/>
            <macro stringvalue="__builtin_huge_valf" flags="-std=c++0x" hide="true"/>
            <macro stringvalue="__builtin_huge_vall" flags="-std=c++0x" hide="true"/>
            <macro stringvalue="__builtin_nan" flags="-std=c++0x" hide="true"/>
            <macro stringvalue="__builtin_fpclassify" flags="-std=c++0x" hide="true"/>

            <macro stringvalue="__builtin_expect(e,x)=e" flags="-std=c++11"/>
            <macro stringvalue="__decltype=decltype" flags="-std=c++11"/>
            <macro stringvalue="__SIZE_TYPE__=unsigned int" flags="-std=c++11"/>
            <macro stringvalue="__PTRDIFF_TYPE__=int" flags="-std=c++11"/>
            <macro stringvalue="__WCHAR_TYPE__=long" flags="-std=c++11"/>
            <macro stringvalue="__gnuc_va_list=va_list" flags="-std=c++11"/>
            <macro stringvalue="_GNU_SOURCE=1" flags="-std=c++11"/>
            <macro stringvalue="__extension__" flags="-std=c++11"/>
            <macro stringvalue="__restrict__" flags="-std=c++11"/>
            <macro stringvalue="__restrict" flags="-std=c++11"/>
            <macro stringvalue="__null=0" flags="-std=c++11"/>
            <macro stringvalue="__GXX_EXPERIMENTAL_CXX0X__=1" flags="-std=c++11"/>
            <macro stringvalue="__SUNPRO_CC_COMPAT='G'" flags="-std=c++11"/>
            <macro stringvalue="__cplusplus=201103L" flags="-std=c++11"/>
            <macro stringvalue="__NOVECTORSIZE__" flags="-std=c++11" hide="true"/>
            <macro stringvalue="_LARGEFILE64_SOURCE" flags="-std=c++11" hide="true"/>
            <macro stringvalue="__builtin_huge_val" flags="-std=c++11" hide="true"/>
            <macro stringvalue="__builtin_huge_valf" flags="-std=c++11" hide="true"/>
            <macro stringvalue="__builtin_huge_vall" flags="-std=c++11" hide="true"/>
            <macro stringvalue="__builtin_nan" flags="-std=c++11" hide="true"/>
            <macro stringvalue="__builtin_fpclassify" flags="-std=c++11" hide="true"/>

            <macro stringvalue="__NOVECTORSIZE__" flags="-xO1" hide="true"/>

            <macro stringvalue="__NOVECTORSIZE__" flags="-xO2" hide="true"/>

            <macro stringvalue="__NOVECTORSIZE__" flags="-xO3" hide="true"/>

            <macro stringvalue="__NOVECTORSIZE__" flags="-xO4" hide="true"/>

            <macro stringvalue="__NOVECTORSIZE__" flags="-xO5" hide="true"/>

            <macro stringvalue="_REENTRANT=1" flags="-xautopar"/>
            <macro stringvalue="__NOVECTORSIZE__" flags="-xautopar" hide="true"/>

            <macro stringvalue="_CHAR_IS_UNSIGNED=1" flags="-xchar=u"/>
            <macro stringvalue="_SIGNEDCHAR_" flags="-xchar=u" hide="true"/>

            <macro stringvalue="_CHAR_IS_UNSIGNED=1" flags="-xchar=unsigned"/>
            <macro stringvalue="_SIGNEDCHAR_" flags="-xchar=unsigned" hide="true"/>

            <macro stringvalue="__NOVECTORSIZE__" flags="-xmaxopt=1" hide="true"/>

            <macro stringvalue="__NOVECTORSIZE__" flags="-xmaxopt=2" hide="true"/>

            <macro stringvalue="__NOVECTORSIZE__" flags="-xmaxopt=3" hide="true"/>

            <macro stringvalue="__NOVECTORSIZE__" flags="-xmaxopt=4" hide="true"/>

            <macro stringvalue="__NOVECTORSIZE__" flags="-xmaxopt=5" hide="true"/>

            <macro stringvalue="_REENTRANT=1" flags="-xopenmp"/>
            <macro stringvalue="_OPENMP=201307L" flags="-xopenmp"/>
            <macro stringvalue="__NOVECTORSIZE__" flags="-xopenmp" hide="true"/>

            <macro stringvalue="_REENTRANT=1" flags="-xopenmp=noopt"/>
            <macro stringvalue="_OPENMP=201307L" flags="-xopenmp=noopt"/>
            <macro stringvalue="__NOVECTORSIZE__" flags="-xopenmp=noopt" hide="true"/>

            <macro stringvalue="_REENTRANT=1" flags="-xopenmp=parallel"/>
            <macro stringvalue="_OPENMP=201307L" flags="-xopenmp=parallel"/>
            <macro stringvalue="__NOVECTORSIZE__" flags="-xopenmp=parallel" hide="true"/>
        </system_macros>
        <user_include flags="-I"/>
        <user_macro flags="-D"/>
        <development_mode>
            <fast_build flags=""/>
            <debug default="true" flags="-g"/>
            <performance_debug flags="-g0 -xO2"/>
            <test_coverage flags="-xprofile=tcov +d -xinline="/>
            <diagnosable_release flags="-g0 -O"/>
            <release flags="-fast -g0"/>
            <performance_release flags="-fast -xipo -xvector=simd -g0"/>
        </development_mode>
        <warning_level>
            <no_warnings flags="-w"/>
            <default default="true" flags=""/>
            <more_warnings flags="+w"/>
            <warning2error flags="-xwe"/>
        </warning_level>
        <architecture>
            <default default="true" flags=""/>
            <bits_32 flags="-m32"/>
            <bits_64 flags="-m64"/>
        </architecture>
        <strip flags="-s"/>
        <multithreading>
            <none default="true" flags=""/>
            <safe flags="-mt"/>
            <automatic flags="-xautopar -xvector -xreduction -xloopinfo -O3"/>
            <open_mp flags="-xopenmp -O3"/>
        </multithreading>
        <standard>
            <old flags="-compat"/>
            <legacy flags="-features=no%localfor,no%extinl,no%conststrings"/>
            <default default="true" flags=""/>
            <modern flags="-features=no%anachronisms,no%transitions,tmplife"/>
        </standard>
        <language_extension>
            <none flags="-features=no%longlong"/>
            <default default="true" flags=""/>
            <all flags="-features=extensions,tmplrefstatic,iddollar"/>
        </language_extension>
        <cpp_standard>
            <default flags="" default="true"/>
            <cpp98 flags=""/>
            <cpp11 flags="-std=c++11"/>
        </cpp_standard>
        <library>
            <none flags="-library=no%Cstd,no%Crun -filt=no%stdlib"/>
            <runtime flags="-library=no%Cstd -filt=no%stdlib"/>
            <classic flags="-library=iostream,no%Cstd -filt=no%stdlib"/>
            <binary_standard default="true" flags=""/>
            <conforming_standard flags="-library=stlport4,no%Cstd"/>
        </library>
        <output_object_file flags="-o "/>
    </cpp>
</toolchaindefinition>
